du2html/__init__.py
du2html/_logging.py
du2html/_options.py
du2html/block.py
du2html/conf.py
du2html/data.py
du2html/duresult.py
du2html/main.py
du2html/render.py
du2html/tcf.py
du2html/util.py
du2html/templates/__init__.py
du2html/templates/temp_treetable.html
du2html/templates/temp_treetable.html.0
du2html/templates/temp_treetable_innerpath.html
du2html-0.0.6.dist-info/LICENSE
du2html-0.0.6.dist-info/METADATA
du2html-0.0.6.dist-info/WHEEL
du2html-0.0.6.dist-info/entry_points.txt
du2html-0.0.6.dist-info/top_level.txt
du2html-0.0.6.dist-info/RECORD
