Metadata-Version: 2.1
Name: du2html
Version: 0.0.6
Summary: UNKNOWN
Home-page: https://github.com/danielmsk/du2html
Author: Daniel Minseok Kwon
Author-email: daniel.minseok.kwon@gmail.com
License: MIT
Keywords: linux,disk usage
Platform: UNKNOWN
Classifier: Operating System :: OS Independent
Classifier: Topic :: Software Development :: Libraries
Classifier: License :: OSI Approved :: MIT License
Classifier: Programming Language :: Python :: 3.4
Classifier: Programming Language :: Python :: 3.5
Classifier: Programming Language :: Python :: 3.6
